charted/__init__.py
charted/charts/__init__.py
charted/charts/axes.py
charted/charts/chart.py
charted/charts/column.py
charted/charts/line.py
charted/charts/scatter.py
charted/commands/create_font_definition.py
charted/commands/create_readme_graphs.py
charted/commands/wip.py
charted/fonts/definitions/Arial.json
charted/fonts/definitions/Helvetica.json
charted/fonts/tkinter.py
charted/fonts/utils.py
charted/html/__init__.py
charted/html/element.py
charted/html/formatter.py
charted/utils/__init__.py
charted/utils/colors.py
charted/utils/defaults.py
charted/utils/exceptions.py
charted/utils/helpers.py
charted/utils/themes.py
charted/utils/transform.py
charted/utils/types.py
charted-0.1.8.dist-info/LICENSE
charted-0.1.8.dist-info/METADATA
charted-0.1.8.dist-info/WHEEL
charted-0.1.8.dist-info/RECORD
